{
  "FormKey": "0169FE:Skyrim.esm",
  "IsCompressed": true,
  "MajorRecordFlagsRaw": 262144,
  "EditorID": "SolitudeFletcher",
  "SkyrimMajorRecordFlags": [
    "Compressed"
  ],
  "Name": {
    "TargetLanguage": "English",
    "Value": "Fletcher"
  },
  "Flags": [
    "IsInteriorCell"
  ],
  "Lighting": {
    "AmbientColor": "#003C3C3C",
    "DirectionalColor": "#00000000",
    "FogNearColor": "#00000000",
    "FogNear": 500.0,
    "FogFar": 10000.0,
    "FogPower": 1.0,
    "AmbientColors": {
      "DirectionalXPlus": "#00553C1C",
      "DirectionalXMinus": "#00553C1C",
      "DirectionalYPlus": "#00553C1C",
      "DirectionalYMinus": "#00553C1C",
      "DirectionalZPlus": "#00553C1C",
      "DirectionalZMinus": "#00553C1C",
      "Specular": "#00000000",
      "Scale": 1.0
    },
    "FogFarColor": "#00000000",
    "FogMax": 0.9,
    "LightFadeBegin": 31000.0,
    "LightFadeEnd": 41000.0,
    "Inherits": [
      "AmbientColor",
      "FogColor",
      "FogNear",
      "FogFar",
      "FogPower",
      "FogMax",
      "LightFadeDistances"
    ]
  },
  "LightingTemplate": "06AB01:Skyrim.esm",
  "WaterHeight": 0.0,
  "Location": "020094:Skyrim.esm",
  "Owner": "0C13E5:Skyrim.esm",
  "LockList": "0C13E6:Skyrim.esm",
  "AcousticSpace": "0E3261:Skyrim.esm",
  "Music": "02C3CA:Skyrim.esm",
  "ImageSpace": "04E666:Skyrim.esm",
  "Temporary": [
    {
      "MutagenObjectType": "PlacedObject",
      "FormKey": "0D6D1B:Skyrim.esm",
      "Base": "0625E0:Skyrim.esm",
      "Radius": 146.34662,
      "Emittance": "02E2CC:Skyrim.esm",
      "LightData": {
        "ShadowDepthBias": 18.126263
      },
      "LocationReference": "020094:Skyrim.esm",
      "Placement": {
        "Position": "-159.37212, -549.1359, 304.34622",
        "Rotation": "3.1415927, 0, 1.553343"
      }
    },
    {
      "MutagenObjectType": "PlacedObject",
      "FormKey": "0D6D20:Skyrim.esm",
      "Base": "0A56A9:Skyrim.esm",
      "Radius": -29.18695,
      "LightData": {
        "FovOffset": -80.0,
        "FadeOffset": -1.0,
        "ShadowDepthBias": 15.355164
      },
      "LocationReference": "020094:Skyrim.esm",
      "Placement": {
        "Position": "-125.13669, -1131.8585, 150.25246",
        "Rotation": "-4.3711385E-08, 0, 1.7584091"
      }
    }
  ],
  "MajorFlags": [
    "0x40000"
  ]
}