{
  "FormKey": "0AE783:Skyrim.esm",
  "IsCompressed": true,
  "MajorRecordFlagsRaw": 262144,
  "EditorID": "WinterholdCollegeMidden02",
  "SkyrimMajorRecordFlags": [
    "Compressed"
  ],
  "Name": {
    "TargetLanguage": "English",
    "Value": "The Midden Dark"
  },
  "Flags": [
    "IsInteriorCell",
    "HasWater"
  ],
  "Lighting": {
    "AmbientColor": "#003C3C3C",
    "DirectionalColor": "#00000000",
    "FogNearColor": "#00000000",
    "FogFar": 5000.0,
    "DirectionalFade": 1.0,
    "AmbientColors": {
      "DirectionalXPlus": "#00553C1C",
      "DirectionalXMinus": "#00553C1C",
      "DirectionalYPlus": "#00553C1C",
      "DirectionalYMinus": "#00553C1C",
      "DirectionalZPlus": "#00553C1C",
      "DirectionalZMinus": "#00553C1C",
      "Specular": "#00000000",
      "Scale": 1.0
    },
    "FogFarColor": "#00000000",
    "LightFadeBegin": 31000.0,
    "LightFadeEnd": 41000.0,
    "Inherits": [
      "AmbientColor",
      "DirectionalColor",
      "FogColor",
      "FogNear",
      "FogPower",
      "FogMax",
      "LightFadeDistances"
    ]
  },
  "LightingTemplate": "01952F:Skyrim.esm",
  "WaterHeight": 0.0,
  "Location": "02BCEB:Skyrim.esm",
  "WaterEnvironmentMap": "Data\\Textures\\Cubemaps\\CaveIceCubeMap_e.dds",
  "AcousticSpace": "02B3AE:Skyrim.esm",
  "EncounterZone": "10D415:Skyrim.esm",
  "Music": "02D4C2:Skyrim.esm",
  "ImageSpace": "0A2687:Skyrim.esm",
  "MajorFlags": [
    "0x40000"
  ]
}