{
  "FormKey": "016A0F:Skyrim.esm",
  "IsCompressed": true,
  "MajorRecordFlagsRaw": 262144,
  "EditorID": "SolitudeRadiantRaiment",
  "SkyrimMajorRecordFlags": [
    "Compressed"
  ],
  "Name": {
    "TargetLanguage": "English",
    "Value": "Radiant Raiment"
  },
  "Flags": [
    "IsInteriorCell"
  ],
  "Lighting": {
    "AmbientColor": "#003C3C3C",
    "DirectionalColor": "#00000000",
    "FogNearColor": "#00000000",
    "FogNear": 500.0,
    "FogFar": 10000.0,
    "FogClipDistance": 2200.0,
    "AmbientColors": {
      "DirectionalXPlus": "#00553C1C",
      "DirectionalXMinus": "#00553C1C",
      "DirectionalYPlus": "#00553C1C",
      "DirectionalYMinus": "#00553C1C",
      "DirectionalZPlus": "#00553C1C",
      "DirectionalZMinus": "#00553C1C",
      "Specular": "#00000000",
      "Scale": 1.0
    },
    "FogFarColor": "#00000000",
    "LightFadeBegin": 31000.0,
    "LightFadeEnd": 41000.0,
    "Inherits": [
      "AmbientColor",
      "FogColor",
      "FogNear",
      "FogFar",
      "FogPower",
      "FogMax",
      "LightFadeDistances"
    ]
  },
  "LightingTemplate": "06256A:Skyrim.esm",
  "WaterHeight": -2.1474836E+09,
  "Location": "02009E:Skyrim.esm",
  "Owner": "0C13F1:Skyrim.esm",
  "LockList": "0C13F2:Skyrim.esm",
  "AcousticSpace": "0C5B6D:Skyrim.esm",
  "Music": "02C3CA:Skyrim.esm",
  "ImageSpace": "0ABDB4:Skyrim.esm",
  "TemporaryUnknownGroupData": 1,
  "Temporary": [
    {
      "MutagenObjectType": "PlacedObject",
      "FormKey": "062662:Skyrim.esm",
      "Base": "0D4C29:Skyrim.esm",
      "LightData": {
        "FadeOffset": 1.133574,
        "ShadowDepthBias": 1.0
      },
      "LocationReference": "02009E:Skyrim.esm",
      "Placement": {
        "Position": "-672, -407.99982, 112"
      }
    },
    {
      "MutagenObjectType": "PlacedObject",
      "FormKey": "0D4F06:Skyrim.esm",
      "Base": "0625E0:Skyrim.esm",
      "Radius": 166.47562,
      "Emittance": "02E2CC:Skyrim.esm",
      "LocationReference": "02009E:Skyrim.esm",
      "Placement": {
        "Position": "-151.38301, -549.8107, 289.8279"
      }
    }
  ],
  "MajorFlags": [
    "0x40000"
  ]
}