{
  "FormKey": "042BEC:Skyrim.esm",
  "IsCompressed": true,
  "MajorRecordFlagsRaw": 262144,
  "EditorID": "Mistwatch03",
  "SkyrimMajorRecordFlags": [
    "Compressed"
  ],
  "Name": {
    "TargetLanguage": "English",
    "Value": "Mistwatch East Tower"
  },
  "Flags": [
    "IsInteriorCell"
  ],
  "Lighting": {
    "AmbientColor": "#00282828",
    "DirectionalColor": "#00000000",
    "FogNearColor": "#00B0DCF7",
    "FogNear": 340.0,
    "FogFar": 14000.0,
    "DirectionalFade": 1.0,
    "AmbientColors": {
      "DirectionalXPlus": "#FFFFFF",
      "DirectionalXMinus": "#FFFFFF",
      "DirectionalYPlus": "#FFFFFF",
      "DirectionalYMinus": "#FFFFFF",
      "DirectionalZPlus": "#FFFFFF",
      "DirectionalZMinus": "#FFFFFF",
      "Specular": "#00B0DCF7",
      "Scale": 1.0
    },
    "FogFarColor": "#00B0DCF7",
    "LightFadeBegin": 31000.0,
    "LightFadeEnd": 41000.0,
    "Inherits": [
      "AmbientColor",
      "DirectionalColor",
      "FogColor",
      "FogNear",
      "FogFar",
      "DirectionalRotation",
      "DirectionalFade",
      "ClipDistance",
      "FogMax",
      "LightFadeDistances"
    ]
  },
  "LightingTemplate": "0B6BC7:Skyrim.esm",
  "WaterHeight": -2.1474836E+09,
  "Location": "01927B:Skyrim.esm",
  "AcousticSpace": "04075D:Skyrim.esm",
  "EncounterZone": "03EC47:Skyrim.esm",
  "Music": "05615B:Skyrim.esm",
  "ImageSpace": "0A2687:Skyrim.esm",
  "MajorFlags": [
    "0x40000"
  ]
}