{
  "FormKey": "013F90:Dawnguard.esm",
  "EditorID": "DLC1ArkngthamzFar",
  "AmbientColor": "#002F291A",
  "DirectionalColor": "#003A555A",
  "FogNearColor": "#00000000",
  "FogNear": 600.0,
  "FogFar": 10000.0,
  "DirectionalRotationZ": 90,
  "DirectionalFade": 1.0,
  "AmbientColors": {
    "DirectionalXPlus": "#0033291D",
    "DirectionalXMinus": "#002A291A",
    "DirectionalYPlus": "#002F2A1C",
    "DirectionalYMinus": "#002F271C",
    "DirectionalZPlus": "#0016130C",
    "DirectionalZMinus": "#005C5138",
    "Specular": "#0067BFE0"
  },
  "FogFarColor": "#00000000",
  "LightFadeStartDistance": 9000.0,
  "LightFadeEndDistance": 10000.0,
  "DirectionalAmbientColors": {
    "DirectionalXPlus": "#0033291B",
    "DirectionalXMinus": "#002A2918",
    "DirectionalYPlus": "#002F2A1A",
    "DirectionalYMinus": "#002F271A",
    "DirectionalZPlus": "#0016130B",
    "DirectionalZMinus": "#00473E28",
    "Specular": "#00000000",
    "Scale": 1.0
  }
}