{
  "FormKey": "0142F3:Dragonborn.esm",
  "IsCompressed": true,
  "MajorRecordFlagsRaw": 262144,
  "EditorID": "DLC2Book03Dungeon",
  "SkyrimMajorRecordFlags": [
    "Compressed"
  ],
  "Name": {
    "TargetLanguage": "English",
    "Value": "Apocrypha"
  },
  "Flags": [
    "IsInteriorCell",
    "HasWater",
    "ShowSky"
  ],
  "Lighting": {
    "AmbientColor": "#00282417",
    "DirectionalColor": "#00000000",
    "FogNearColor": "#004B6361",
    "FogFar": 4500.0,
    "AmbientColors": {
      "DirectionalXPlus": "#001D1810",
      "DirectionalXMinus": "#0018180F",
      "DirectionalYPlus": "#001B1910",
      "DirectionalYMinus": "#001B1610",
      "DirectionalZPlus": "#000C0B07",
      "DirectionalZMinus": "#00292418",
      "Specular": "#00000000",
      "Scale": 1.0
    },
    "FogFarColor": "#00787C58",
    "LightFadeBegin": 31000.0,
    "LightFadeEnd": 41000.0,
    "Inherits": [
      "AmbientColor",
      "DirectionalColor",
      "FogColor",
      "FogNear",
      "FogFar",
      "DirectionalRotation",
      "DirectionalFade",
      "ClipDistance",
      "FogPower",
      "LightFadeDistances"
    ]
  },
  "LightingTemplate": "034C19:Dragonborn.esm",
  "WaterHeight": 0.0,
  "Location": "0142AF:Dragonborn.esm",
  "Water": "01DFF1:Dragonborn.esm",
  "WaterEnvironmentMap": "data\\Textures\\Cubemaps\\Apocrypha.dds",
  "SkyAndWeatherFromRegion": "071E66:Skyrim.esm",
  "AcousticSpace": "039E50:Dragonborn.esm",
  "EncounterZone": "0142B2:Dragonborn.esm",
  "Music": "034281:Dragonborn.esm",
  "ImageSpace": "01C48C:Dragonborn.esm",
  "MajorFlags": [
    "0x40000"
  ]
}