{
  "FormKey": "013978:Skyrim.esm",
  "IsCompressed": true,
  "MajorRecordFlagsRaw": 262144,
  "EditorID": "KarthwastenFennsGulchMine",
  "SkyrimMajorRecordFlags": [
    "Compressed"
  ],
  "Name": {
    "TargetLanguage": "English",
    "Value": "Fenn's Gulch Mine"
  },
  "Flags": [
    "IsInteriorCell",
    "PublicArea"
  ],
  "Lighting": {
    "AmbientColor": "#00302B21",
    "DirectionalColor": "#001E1A17",
    "FogNearColor": "#00B0DCF7",
    "FogNear": 340.0,
    "FogFar": 8000.0,
    "AmbientColors": {
      "DirectionalXPlus": "#00342B22",
      "DirectionalXMinus": "#002B2B1F",
      "DirectionalYPlus": "#00302D21",
      "DirectionalYMinus": "#00302821",
      "DirectionalZPlus": "#0016140E",
      "DirectionalZMinus": "#00494133",
      "Specular": "#00000000",
      "Scale": 1.0
    },
    "FogFarColor": "#00B0DCF7",
    "LightFadeBegin": 31000.0,
    "LightFadeEnd": 41000.0,
    "Inherits": [
      "AmbientColor",
      "DirectionalColor",
      "FogColor",
      "FogNear",
      "DirectionalRotation",
      "DirectionalFade",
      "ClipDistance",
      "FogPower",
      "FogMax",
      "LightFadeDistances"
    ]
  },
  "LightingTemplate": "091937:Skyrim.esm",
  "WaterHeight": -2.1474836E+09,
  "Location": "01F7BE:Skyrim.esm",
  "AcousticSpace": "0FD93A:Skyrim.esm",
  "Music": "05615B:Skyrim.esm",
  "ImageSpace": "0A2687:Skyrim.esm",
  "MajorFlags": [
    "0x40000"
  ]
}